{
  "date" : "Wed, 16 Apr, 2025 12:37:22 +0000",
  "doco" : "For each file: start is seconds after start activity occurred. Length = milliseconds activity took",
  "files" : [
    {
      "name" : "/fsh-generated/resources/ImplementationGuide-hl7.fhir.be.pss.json",
      "size" : 30122,
      "processes" : [
        {
          "activity" : "load",
          "start" : 53,
          "length" : 16
        },
        {
          "activity" : "checkR4R4B",
          "start" : 55,
          "length" : 6
        },
        {
          "activity" : "generateNarratives",
          "start" : 55,
          "length" : 419
        },
        {
          "activity" : "validate",
          "start" : 71,
          "length" : 5948
        },
        {
          "activity" : "scanForUsageStats",
          "start" : 79,
          "length" : 1
        },
        {
          "activity" : "generate1",
          "start" : 85,
          "length" : 132
        },
        {
          "activity" : "generate2",
          "start" : 92,
          "length" : 183
        },
        {
          "activity" : "generateValidationPack",
          "start" : 118,
          "length" : 6
        },
        {
          "activity" : "scanExamplesForR5",
          "start" : 129,
          "length" : 1
        }
      ]
    },
    {
      "name" : "fsh-generated/resources/AllergyIntolerance-allergy-to-sulfonamide.json",
      "size" : 482,
      "processes" : [
        {
          "activity" : "loadResources",
          "start" : 52,
          "length" : 4
        },
        {
          "activity" : "load-configure",
          "start" : 55,
          "length" : 1
        },
        {
          "activity" : "generateNarratives",
          "start" : 56,
          "length" : 41
        },
        {
          "activity" : "validate",
          "start" : 79,
          "length" : 200
        },
        {
          "activity" : "generate1",
          "start" : 86,
          "length" : 18
        },
        {
          "activity" : "generate2",
          "start" : 92,
          "length" : 18
        }
      ]
    },
    {
      "name" : "fsh-generated/resources/Bundle-getdatatocollect-a-data.json",
      "size" : 3919,
      "processes" : [
        {
          "activity" : "loadResources",
          "start" : 52,
          "length" : 4
        },
        {
          "activity" : "load",
          "start" : 52,
          "length" : 25
        },
        {
          "activity" : "checkR4R4B",
          "start" : 55,
          "length" : 1
        },
        {
          "activity" : "generateNarratives",
          "start" : 56,
          "length" : 387
        },
        {
          "activity" : "validate",
          "start" : 79,
          "length" : 415
        },
        {
          "activity" : "generate1",
          "start" : 86,
          "length" : 22
        },
        {
          "activity" : "generate2",
          "start" : 92,
          "length" : 22
        }
      ]
    },
    {
      "name" : "fsh-generated/resources/Bundle-getdatatocollect-a-response.json",
      "size" : 16651,
      "processes" : [
        {
          "activity" : "loadResources",
          "start" : 52,
          "length" : 7
        },
        {
          "activity" : "load",
          "start" : 52,
          "length" : 14
        },
        {
          "activity" : "load",
          "start" : 52,
          "length" : 4
        },
        {
          "activity" : "load",
          "start" : 52,
          "length" : 5
        },
        {
          "activity" : "load",
          "start" : 53,
          "length" : 4
        },
        {
          "activity" : "load",
          "start" : 53,
          "length" : 4
        },
        {
          "activity" : "load",
          "start" : 53,
          "length" : 4
        },
        {
          "activity" : "load",
          "start" : 53,
          "length" : 4
        },
        {
          "activity" : "load",
          "start" : 53,
          "length" : 3
        },
        {
          "activity" : "load",
          "start" : 53,
          "length" : 3
        },
        {
          "activity" : "load",
          "start" : 53,
          "length" : 3
        },
        {
          "activity" : "load",
          "start" : 53,
          "length" : 3
        },
        {
          "activity" : "load",
          "start" : 53,
          "length" : 3
        },
        {
          "activity" : "load",
          "start" : 53,
          "length" : 4
        },
        {
          "activity" : "load",
          "start" : 53,
          "length" : 4
        },
        {
          "activity" : "load",
          "start" : 53,
          "length" : 3
        },
        {
          "activity" : "load",
          "start" : 53,
          "length" : 3
        },
        {
          "activity" : "load",
          "start" : 53,
          "length" : 4
        },
        {
          "activity" : "load",
          "start" : 53,
          "length" : 4
        },
        {
          "activity" : "load",
          "start" : 53,
          "length" : 3
        },
        {
          "activity" : "load",
          "start" : 53,
          "length" : 3
        },
        {
          "activity" : "load",
          "start" : 53,
          "length" : 4
        },
        {
          "activity" : "load",
          "start" : 53,
          "length" : 4
        },
        {
          "activity" : "load",
          "start" : 53,
          "length" : 4
        },
        {
          "activity" : "load",
          "start" : 53,
          "length" : 4
        },
        {
          "activity" : "load",
          "start" : 53,
          "length" : 3
        },
        {
          "activity" : "load",
          "start" : 53,
          "length" : 3
        },
        {
          "activity" : "load",
          "start" : 53,
          "length" : 3
        },
        {
          "activity" : "load",
          "start" : 53,
          "length" : 3
        },
        {
          "activity" : "load",
          "start" : 53,
          "length" : 4
        },
        {
          "activity" : "load",
          "start" : 53,
          "length" : 3
        },
        {
          "activity" : "load",
          "start" : 53,
          "length" : 3
        },
        {
          "activity" : "load",
          "start" : 53,
          "length" : 3
        },
        {
          "activity" : "load",
          "start" : 53,
          "length" : 3
        },
        {
          "activity" : "load",
          "start" : 53,
          "length" : 3
        },
        {
          "activity" : "load",
          "start" : 53,
          "length" : 3
        },
        {
          "activity" : "load",
          "start" : 53,
          "length" : 3
        },
        {
          "activity" : "load",
          "start" : 53,
          "length" : 3
        },
        {
          "activity" : "load",
          "start" : 53,
          "length" : 3
        },
        {
          "activity" : "load",
          "start" : 53,
          "length" : 3
        },
        {
          "activity" : "load",
          "start" : 53,
          "length" : 3
        },
        {
          "activity" : "checkR4R4B",
          "start" : 55,
          "length" : 1
        },
        {
          "activity" : "generateNarratives",
          "start" : 56,
          "length" : 23
        },
        {
          "activity" : "validate",
          "start" : 79,
          "length" : 198
        },
        {
          "activity" : "generate1",
          "start" : 86,
          "length" : 56
        },
        {
          "activity" : "generate2",
          "start" : 92,
          "length" : 46
        }
      ]
    },
    {
      "name" : "fsh-generated/resources/Bundle-getrecommendations-a-data.json",
      "size" : 5633,
      "processes" : [
        {
          "activity" : "loadResources",
          "start" : 52,
          "length" : 5
        },
        {
          "activity" : "load",
          "start" : 52,
          "length" : 8
        },
        {
          "activity" : "generateNarratives",
          "start" : 56,
          "length" : 6
        },
        {
          "activity" : "validate",
          "start" : 79,
          "length" : 34
        },
        {
          "activity" : "generate1",
          "start" : 86,
          "length" : 35
        },
        {
          "activity" : "generate2",
          "start" : 92,
          "length" : 29
        }
      ]
    },
    {
      "name" : "fsh-generated/resources/Bundle-getrecommendations-a-response.json",
      "size" : 22127,
      "processes" : [
        {
          "activity" : "loadResources",
          "start" : 52,
          "length" : 5
        },
        {
          "activity" : "load",
          "start" : 52,
          "length" : 11
        },
        {
          "activity" : "load",
          "start" : 52,
          "length" : 5
        },
        {
          "activity" : "load",
          "start" : 52,
          "length" : 5
        },
        {
          "activity" : "load",
          "start" : 53,
          "length" : 5
        },
        {
          "activity" : "load",
          "start" : 53,
          "length" : 5
        },
        {
          "activity" : "load",
          "start" : 53,
          "length" : 4
        },
        {
          "activity" : "load",
          "start" : 53,
          "length" : 4
        },
        {
          "activity" : "load",
          "start" : 53,
          "length" : 5
        },
        {
          "activity" : "load",
          "start" : 53,
          "length" : 5
        },
        {
          "activity" : "load",
          "start" : 53,
          "length" : 4
        },
        {
          "activity" : "load",
          "start" : 53,
          "length" : 5
        },
        {
          "activity" : "load",
          "start" : 53,
          "length" : 4
        },
        {
          "activity" : "load",
          "start" : 53,
          "length" : 3
        },
        {
          "activity" : "load",
          "start" : 53,
          "length" : 4
        },
        {
          "activity" : "load",
          "start" : 53,
          "length" : 4
        },
        {
          "activity" : "load",
          "start" : 53,
          "length" : 4
        },
        {
          "activity" : "load",
          "start" : 53,
          "length" : 4
        },
        {
          "activity" : "load",
          "start" : 53,
          "length" : 4
        },
        {
          "activity" : "load",
          "start" : 53,
          "length" : 4
        },
        {
          "activity" : "load",
          "start" : 53,
          "length" : 4
        },
        {
          "activity" : "load",
          "start" : 53,
          "length" : 4
        },
        {
          "activity" : "load",
          "start" : 53,
          "length" : 3
        },
        {
          "activity" : "load",
          "start" : 53,
          "length" : 4
        },
        {
          "activity" : "load",
          "start" : 53,
          "length" : 4
        },
        {
          "activity" : "load",
          "start" : 53,
          "length" : 4
        },
        {
          "activity" : "load",
          "start" : 53,
          "length" : 4
        },
        {
          "activity" : "load",
          "start" : 53,
          "length" : 4
        },
        {
          "activity" : "load",
          "start" : 53,
          "length" : 4
        },
        {
          "activity" : "load",
          "start" : 53,
          "length" : 3
        },
        {
          "activity" : "load",
          "start" : 53,
          "length" : 4
        },
        {
          "activity" : "load",
          "start" : 53,
          "length" : 3
        },
        {
          "activity" : "load",
          "start" : 53,
          "length" : 3
        },
        {
          "activity" : "load",
          "start" : 53,
          "length" : 4
        },
        {
          "activity" : "load",
          "start" : 53,
          "length" : 3
        },
        {
          "activity" : "load",
          "start" : 53,
          "length" : 3
        },
        {
          "activity" : "load",
          "start" : 53,
          "length" : 3
        },
        {
          "activity" : "load",
          "start" : 53,
          "length" : 3
        },
        {
          "activity" : "load",
          "start" : 53,
          "length" : 3
        },
        {
          "activity" : "load",
          "start" : 53,
          "length" : 4
        },
        {
          "activity" : "load",
          "start" : 53,
          "length" : 4
        },
        {
          "activity" : "checkR4R4B",
          "start" : 55,
          "length" : 1
        },
        {
          "activity" : "generateNarratives",
          "start" : 56,
          "length" : 214
        },
        {
          "activity" : "scanForUsageStats",
          "start" : 79,
          "length" : 1
        },
        {
          "activity" : "validate",
          "start" : 79,
          "length" : 2929
        },
        {
          "activity" : "generate1",
          "start" : 86,
          "length" : 40
        },
        {
          "activity" : "generate2",
          "start" : 92,
          "length" : 64
        }
      ]
    },
    {
      "name" : "fsh-generated/resources/Bundle-getrecommendations-data3.json",
      "size" : 3581,
      "processes" : [
        {
          "activity" : "loadResources",
          "start" : 52,
          "length" : 3
        },
        {
          "activity" : "load",
          "start" : 52,
          "length" : 12
        },
        {
          "activity" : "load",
          "start" : 53,
          "length" : 1
        },
        {
          "activity" : "generateNarratives",
          "start" : 56,
          "length" : 7
        },
        {
          "activity" : "validate",
          "start" : 82,
          "length" : 401
        },
        {
          "activity" : "generate1",
          "start" : 86,
          "length" : 17
        },
        {
          "activity" : "generate2",
          "start" : 93,
          "length" : 28
        }
      ]
    },
    {
      "name" : "fsh-generated/resources/Bundle-getrecommendations-r-response.json",
      "size" : 9572,
      "processes" : [
        {
          "activity" : "loadResources",
          "start" : 52,
          "length" : 4
        },
        {
          "activity" : "load",
          "start" : 52,
          "length" : 3
        },
        {
          "activity" : "load",
          "start" : 52,
          "length" : 3
        },
        {
          "activity" : "load",
          "start" : 52,
          "length" : 3
        },
        {
          "activity" : "load",
          "start" : 53,
          "length" : 3
        },
        {
          "activity" : "load",
          "start" : 53,
          "length" : 3
        },
        {
          "activity" : "load",
          "start" : 53,
          "length" : 3
        },
        {
          "activity" : "load",
          "start" : 53,
          "length" : 3
        },
        {
          "activity" : "load",
          "start" : 53,
          "length" : 3
        },
        {
          "activity" : "load",
          "start" : 53,
          "length" : 2
        },
        {
          "activity" : "load",
          "start" : 53,
          "length" : 2
        },
        {
          "activity" : "load",
          "start" : 53,
          "length" : 2
        },
        {
          "activity" : "load",
          "start" : 53,
          "length" : 3
        },
        {
          "activity" : "load",
          "start" : 53,
          "length" : 3
        },
        {
          "activity" : "load",
          "start" : 53,
          "length" : 3
        },
        {
          "activity" : "load",
          "start" : 53,
          "length" : 3
        },
        {
          "activity" : "load",
          "start" : 53,
          "length" : 3
        },
        {
          "activity" : "load",
          "start" : 53,
          "length" : 2
        },
        {
          "activity" : "load",
          "start" : 53,
          "length" : 2
        },
        {
          "activity" : "load",
          "start" : 53,
          "length" : 3
        },
        {
          "activity" : "load",
          "start" : 53,
          "length" : 3
        },
        {
          "activity" : "load",
          "start" : 53,
          "length" : 2
        },
        {
          "activity" : "load",
          "start" : 53,
          "length" : 3
        },
        {
          "activity" : "load",
          "start" : 53,
          "length" : 2
        },
        {
          "activity" : "load",
          "start" : 53,
          "length" : 2
        },
        {
          "activity" : "load",
          "start" : 53,
          "length" : 3
        },
        {
          "activity" : "load",
          "start" : 53,
          "length" : 3
        },
        {
          "activity" : "load",
          "start" : 53,
          "length" : 3
        },
        {
          "activity" : "load",
          "start" : 53,
          "length" : 2
        },
        {
          "activity" : "load",
          "start" : 53,
          "length" : 3
        },
        {
          "activity" : "load",
          "start" : 53,
          "length" : 3
        },
        {
          "activity" : "load",
          "start" : 53,
          "length" : 3
        },
        {
          "activity" : "load",
          "start" : 53,
          "length" : 3
        },
        {
          "activity" : "load",
          "start" : 53,
          "length" : 3
        },
        {
          "activity" : "load",
          "start" : 53,
          "length" : 3
        },
        {
          "activity" : "load",
          "start" : 53,
          "length" : 3
        },
        {
          "activity" : "load",
          "start" : 53,
          "length" : 3
        },
        {
          "activity" : "load",
          "start" : 53,
          "length" : 3
        },
        {
          "activity" : "load",
          "start" : 53,
          "length" : 3
        },
        {
          "activity" : "load",
          "start" : 53,
          "length" : 2
        },
        {
          "activity" : "load",
          "start" : 53,
          "length" : 2
        },
        {
          "activity" : "checkR4R4B",
          "start" : 55,
          "length" : 1
        },
        {
          "activity" : "generateNarratives",
          "start" : 56,
          "length" : 12
        },
        {
          "activity" : "validate",
          "start" : 83,
          "length" : 939
        },
        {
          "activity" : "generate1",
          "start" : 86,
          "length" : 22
        },
        {
          "activity" : "generate2",
          "start" : 93,
          "length" : 45
        }
      ]
    },
    {
      "name" : "fsh-generated/resources/Bundle-radiology-getdiagnoses-response.json",
      "size" : 14092,
      "processes" : [
        {
          "activity" : "loadResources",
          "start" : 52,
          "length" : 5
        },
        {
          "activity" : "load",
          "start" : 52,
          "length" : 6
        },
        {
          "activity" : "load",
          "start" : 52,
          "length" : 3
        },
        {
          "activity" : "load",
          "start" : 52,
          "length" : 4
        },
        {
          "activity" : "load",
          "start" : 53,
          "length" : 4
        },
        {
          "activity" : "load",
          "start" : 53,
          "length" : 4
        },
        {
          "activity" : "load",
          "start" : 53,
          "length" : 4
        },
        {
          "activity" : "load",
          "start" : 53,
          "length" : 4
        },
        {
          "activity" : "load",
          "start" : 53,
          "length" : 3
        },
        {
          "activity" : "load",
          "start" : 53,
          "length" : 4
        },
        {
          "activity" : "load",
          "start" : 53,
          "length" : 4
        },
        {
          "activity" : "load",
          "start" : 53,
          "length" : 4
        },
        {
          "activity" : "load",
          "start" : 53,
          "length" : 3
        },
        {
          "activity" : "load",
          "start" : 53,
          "length" : 3
        },
        {
          "activity" : "load",
          "start" : 53,
          "length" : 3
        },
        {
          "activity" : "load",
          "start" : 53,
          "length" : 3
        },
        {
          "activity" : "load",
          "start" : 53,
          "length" : 3
        },
        {
          "activity" : "load",
          "start" : 53,
          "length" : 9
        },
        {
          "activity" : "load",
          "start" : 53,
          "length" : 3
        },
        {
          "activity" : "load",
          "start" : 53,
          "length" : 3
        },
        {
          "activity" : "load",
          "start" : 53,
          "length" : 3
        },
        {
          "activity" : "load",
          "start" : 53,
          "length" : 3
        },
        {
          "activity" : "load",
          "start" : 53,
          "length" : 3
        },
        {
          "activity" : "load",
          "start" : 53,
          "length" : 3
        },
        {
          "activity" : "load",
          "start" : 53,
          "length" : 3
        },
        {
          "activity" : "load",
          "start" : 53,
          "length" : 3
        },
        {
          "activity" : "load",
          "start" : 53,
          "length" : 3
        },
        {
          "activity" : "load",
          "start" : 53,
          "length" : 3
        },
        {
          "activity" : "load",
          "start" : 53,
          "length" : 4
        },
        {
          "activity" : "load",
          "start" : 53,
          "length" : 3
        },
        {
          "activity" : "load",
          "start" : 53,
          "length" : 3
        },
        {
          "activity" : "load",
          "start" : 53,
          "length" : 3
        },
        {
          "activity" : "load",
          "start" : 53,
          "length" : 3
        },
        {
          "activity" : "load",
          "start" : 53,
          "length" : 3
        },
        {
          "activity" : "load",
          "start" : 53,
          "length" : 3
        },
        {
          "activity" : "load",
          "start" : 53,
          "length" : 3
        },
        {
          "activity" : "load",
          "start" : 53,
          "length" : 3
        },
        {
          "activity" : "load",
          "start" : 53,
          "length" : 3
        },
        {
          "activity" : "load",
          "start" : 53,
          "length" : 3
        },
        {
          "activity" : "load",
          "start" : 53,
          "length" : 3
        },
        {
          "activity" : "load",
          "start" : 53,
          "length" : 3
        },
        {
          "activity" : "generateNarratives",
          "start" : 56,
          "length" : 22
        },
        {
          "activity" : "validate",
          "start" : 84,
          "length" : 804
        },
        {
          "activity" : "generate1",
          "start" : 86,
          "length" : 41
        },
        {
          "activity" : "generate2",
          "start" : 93,
          "length" : 70
        }
      ]
    },
    {
      "name" : "fsh-generated/resources/Bundle-radiology-getdiagnoses.json",
      "size" : 2466,
      "processes" : [
        {
          "activity" : "loadResources",
          "start" : 52,
          "length" : 3
        },
        {
          "activity" : "load",
          "start" : 52,
          "length" : 8
        },
        {
          "activity" : "load",
          "start" : 52,
          "length" : 1
        },
        {
          "activity" : "generateNarratives",
          "start" : 56,
          "length" : 3
        },
        {
          "activity" : "validate",
          "start" : 84,
          "length" : 200
        },
        {
          "activity" : "generate1",
          "start" : 86,
          "length" : 19
        },
        {
          "activity" : "generate2",
          "start" : 93,
          "length" : 21
        }
      ]
    },
    {
      "name" : "fsh-generated/resources/CodeSystem-PSSQSIConditions.json",
      "size" : 374,
      "processes" : [
        {
          "activity" : "loadResources",
          "start" : 52,
          "length" : 2
        },
        {
          "activity" : "load",
          "start" : 52,
          "length" : 14
        },
        {
          "activity" : "generateNarratives",
          "start" : 56,
          "length" : 9
        },
        {
          "activity" : "validate",
          "start" : 62,
          "length" : 1040
        },
        {
          "activity" : "generate1",
          "start" : 86,
          "length" : 13
        },
        {
          "activity" : "generate2",
          "start" : 93,
          "length" : 2370
        },
        {
          "activity" : "generateValidationPack",
          "start" : 118,
          "length" : 1
        },
        {
          "activity" : "scanExamplesForR5",
          "start" : 129,
          "length" : 1
        }
      ]
    },
    {
      "name" : "fsh-generated/resources/CodeSystem-PSSQSIProcedures.json",
      "size" : 374,
      "processes" : [
        {
          "activity" : "loadResources",
          "start" : 52,
          "length" : 2
        },
        {
          "activity" : "load",
          "start" : 52,
          "length" : 4
        },
        {
          "activity" : "generateNarratives",
          "start" : 56,
          "length" : 7
        },
        {
          "activity" : "validate",
          "start" : 63,
          "length" : 8
        },
        {
          "activity" : "generate1",
          "start" : 86,
          "length" : 12
        },
        {
          "activity" : "generate2",
          "start" : 95,
          "length" : 59
        }
      ]
    },
    {
      "name" : "fsh-generated/resources/CodeSystem-PSSRatingTypes.json",
      "size" : 611,
      "processes" : [
        {
          "activity" : "loadResources",
          "start" : 52,
          "length" : 3
        },
        {
          "activity" : "load",
          "start" : 52,
          "length" : 6
        },
        {
          "activity" : "generateNarratives",
          "start" : 56,
          "length" : 8
        },
        {
          "activity" : "validate",
          "start" : 63,
          "length" : 9
        },
        {
          "activity" : "generate1",
          "start" : 86,
          "length" : 19
        },
        {
          "activity" : "generate2",
          "start" : 95,
          "length" : 56
        },
        {
          "activity" : "generateValidationPack",
          "start" : 118,
          "length" : 1
        }
      ]
    },
    {
      "name" : "fsh-generated/resources/CommunicationRequest-ab-advice.json",
      "size" : 1901,
      "processes" : [
        {
          "activity" : "loadResources",
          "start" : 52,
          "length" : 2
        },
        {
          "activity" : "generateNarratives",
          "start" : 56,
          "length" : 3
        },
        {
          "activity" : "validate",
          "start" : 85,
          "length" : 28
        },
        {
          "activity" : "generate1",
          "start" : 86,
          "length" : 18
        },
        {
          "activity" : "generate2",
          "start" : 95,
          "length" : 15
        }
      ]
    },
    {
      "name" : "fsh-generated/resources/Condition-proposed-diagnosis-3074219.json",
      "size" : 1073,
      "processes" : [
        {
          "activity" : "loadResources",
          "start" : 52,
          "length" : 4
        },
        {
          "activity" : "load-configure",
          "start" : 55,
          "length" : 1
        },
        {
          "activity" : "generateNarratives",
          "start" : 56,
          "length" : 1
        },
        {
          "activity" : "validate",
          "start" : 85,
          "length" : 4
        },
        {
          "activity" : "generate1",
          "start" : 86,
          "length" : 17
        },
        {
          "activity" : "generate2",
          "start" : 95,
          "length" : 8
        }
      ]
    },
    {
      "name" : "fsh-generated/resources/Condition-proposed-diagnosis-3074220.json",
      "size" : 1054,
      "processes" : [
        {
          "activity" : "loadResources",
          "start" : 52,
          "length" : 4
        },
        {
          "activity" : "generateNarratives",
          "start" : 56,
          "length" : 1
        },
        {
          "activity" : "validate",
          "start" : 85,
          "length" : 3
        },
        {
          "activity" : "generate1",
          "start" : 86,
          "length" : 12
        },
        {
          "activity" : "generate2",
          "start" : 95,
          "length" : 8
        }
      ]
    },
    {
      "name" : "fsh-generated/resources/Condition-proposed-diagnosis-3074221.json",
      "size" : 1057,
      "processes" : [
        {
          "activity" : "loadResources",
          "start" : 52,
          "length" : 2
        },
        {
          "activity" : "generateNarratives",
          "start" : 56,
          "length" : 2
        },
        {
          "activity" : "validate",
          "start" : 85,
          "length" : 3
        },
        {
          "activity" : "generate1",
          "start" : 86,
          "length" : 10
        },
        {
          "activity" : "generate2",
          "start" : 95,
          "length" : 8
        }
      ]
    },
    {
      "name" : "fsh-generated/resources/Condition-proposed-diagnosis-3074222.json",
      "size" : 1054,
      "processes" : [
        {
          "activity" : "loadResources",
          "start" : 52,
          "length" : 3
        },
        {
          "activity" : "checkR4R4B",
          "start" : 55,
          "length" : 1
        },
        {
          "activity" : "generateNarratives",
          "start" : 56,
          "length" : 1
        },
        {
          "activity" : "validate",
          "start" : 85,
          "length" : 4
        },
        {
          "activity" : "generate1",
          "start" : 86,
          "length" : 11
        },
        {
          "activity" : "generate2",
          "start" : 95,
          "length" : 8
        }
      ]
    },
    {
      "name" : "fsh-generated/resources/Condition-proposed-diagnosis-5000246.json",
      "size" : 1049,
      "processes" : [
        {
          "activity" : "loadResources",
          "start" : 52,
          "length" : 2
        },
        {
          "activity" : "scan",
          "start" : 55,
          "length" : 1
        },
        {
          "activity" : "generateNarratives",
          "start" : 56,
          "length" : 2
        },
        {
          "activity" : "validate",
          "start" : 85,
          "length" : 5
        },
        {
          "activity" : "generate1",
          "start" : 86,
          "length" : 13
        },
        {
          "activity" : "generate2",
          "start" : 95,
          "length" : 11
        }
      ]
    },
    {
      "name" : "fsh-generated/resources/Condition-pss-proposed-diagnosis-5000246.json",
      "size" : 1061,
      "processes" : [
        {
          "activity" : "loadResources",
          "start" : 52,
          "length" : 2
        },
        {
          "activity" : "load",
          "start" : 53,
          "length" : 1
        },
        {
          "activity" : "generateNarratives",
          "start" : 56,
          "length" : 1
        },
        {
          "activity" : "validate",
          "start" : 85,
          "length" : 3
        },
        {
          "activity" : "generate1",
          "start" : 86,
          "length" : 12
        },
        {
          "activity" : "generate2",
          "start" : 95,
          "length" : 8
        }
      ]
    },
    {
      "name" : "fsh-generated/resources/Condition-vulvovaginitis.json",
      "size" : 1088,
      "processes" : [
        {
          "activity" : "loadResources",
          "start" : 52,
          "length" : 3
        },
        {
          "activity" : "generateNarratives",
          "start" : 56,
          "length" : 1
        },
        {
          "activity" : "validate",
          "start" : 85,
          "length" : 4
        },
        {
          "activity" : "generate1",
          "start" : 86,
          "length" : 10
        },
        {
          "activity" : "generate2",
          "start" : 95,
          "length" : 7
        }
      ]
    },
    {
      "name" : "fsh-generated/resources/MedicationRequest-clindamycin.json",
      "size" : 1117,
      "processes" : [
        {
          "activity" : "loadResources",
          "start" : 52,
          "length" : 2
        },
        {
          "activity" : "generateNarratives",
          "start" : 56,
          "length" : 1
        },
        {
          "activity" : "validate",
          "start" : 85,
          "length" : 7
        },
        {
          "activity" : "generate1",
          "start" : 86,
          "length" : 15
        },
        {
          "activity" : "generate2",
          "start" : 95,
          "length" : 9
        }
      ]
    },
    {
      "name" : "fsh-generated/resources/MedicationRequest-fluconazol.json",
      "size" : 347,
      "processes" : [
        {
          "activity" : "loadResources",
          "start" : 52,
          "length" : 3
        },
        {
          "activity" : "generateNarratives",
          "start" : 56,
          "length" : 1
        },
        {
          "activity" : "validate",
          "start" : 85,
          "length" : 1
        },
        {
          "activity" : "generate1",
          "start" : 86,
          "length" : 9
        },
        {
          "activity" : "generate2",
          "start" : 95,
          "length" : 10
        },
        {
          "activity" : "generateExampleZip",
          "start" : 118,
          "length" : 1
        }
      ]
    },
    {
      "name" : "fsh-generated/resources/MedicationRequest-metronidazol.json",
      "size" : 1459,
      "processes" : [
        {
          "activity" : "loadResources",
          "start" : 52,
          "length" : 2
        },
        {
          "activity" : "load-configure",
          "start" : 55,
          "length" : 1
        },
        {
          "activity" : "generateNarratives",
          "start" : 56,
          "length" : 1
        },
        {
          "activity" : "validate",
          "start" : 85,
          "length" : 8
        },
        {
          "activity" : "generate1",
          "start" : 86,
          "length" : 10
        },
        {
          "activity" : "generate2",
          "start" : 95,
          "length" : 17
        }
      ]
    },
    {
      "name" : "fsh-generated/resources/MedicationRequest-miconazol.json",
      "size" : 450,
      "processes" : [
        {
          "activity" : "loadResources",
          "start" : 52,
          "length" : 2
        },
        {
          "activity" : "generateNarratives",
          "start" : 56,
          "length" : 2
        },
        {
          "activity" : "validate",
          "start" : 85,
          "length" : 3
        },
        {
          "activity" : "generate1",
          "start" : 86,
          "length" : 9
        },
        {
          "activity" : "generate2",
          "start" : 95,
          "length" : 8
        }
      ]
    },
    {
      "name" : "fsh-generated/resources/MedicationRequest-proposal-clindamycin.json",
      "size" : 324,
      "processes" : [
        {
          "activity" : "loadResources",
          "start" : 52,
          "length" : 3
        },
        {
          "activity" : "validate",
          "start" : 85,
          "length" : 1
        },
        {
          "activity" : "generate1",
          "start" : 86,
          "length" : 9
        },
        {
          "activity" : "generate2",
          "start" : 95,
          "length" : 7
        }
      ]
    },
    {
      "name" : "fsh-generated/resources/Observation-ataxia.json",
      "size" : 287,
      "processes" : [
        {
          "activity" : "loadResources",
          "start" : 52,
          "length" : 2
        },
        {
          "activity" : "generateNarratives",
          "start" : 56,
          "length" : 1
        },
        {
          "activity" : "validate",
          "start" : 85,
          "length" : 1
        },
        {
          "activity" : "generate1",
          "start" : 86,
          "length" : 8
        },
        {
          "activity" : "generate2",
          "start" : 95,
          "length" : 7
        }
      ]
    },
    {
      "name" : "fsh-generated/resources/Patient-patient-a.json",
      "size" : 684,
      "processes" : [
        {
          "activity" : "loadResources",
          "start" : 52,
          "length" : 3
        },
        {
          "activity" : "generateNarratives",
          "start" : 56,
          "length" : 1
        },
        {
          "activity" : "validate",
          "start" : 85,
          "length" : 6
        },
        {
          "activity" : "generate1",
          "start" : 86,
          "length" : 10
        },
        {
          "activity" : "generate2",
          "start" : 95,
          "length" : 7
        }
      ]
    },
    {
      "name" : "fsh-generated/resources/Patient-patient-r.json",
      "size" : 682,
      "processes" : [
        {
          "activity" : "loadResources",
          "start" : 52,
          "length" : 3
        },
        {
          "activity" : "generateNarratives",
          "start" : 56,
          "length" : 1
        },
        {
          "activity" : "scanForUsageStats",
          "start" : 79,
          "length" : 1
        },
        {
          "activity" : "validate",
          "start" : 85,
          "length" : 5
        },
        {
          "activity" : "generate1",
          "start" : 86,
          "length" : 9
        },
        {
          "activity" : "generate2",
          "start" : 95,
          "length" : 7
        }
      ]
    },
    {
      "name" : "fsh-generated/resources/PlanDefinition-GetDataToCollect.json",
      "size" : 2832,
      "processes" : [
        {
          "activity" : "loadResources",
          "start" : 52,
          "length" : 2
        },
        {
          "activity" : "load",
          "start" : 53,
          "length" : 22
        },
        {
          "activity" : "generateNarratives",
          "start" : 56,
          "length" : 24
        },
        {
          "activity" : "validate",
          "start" : 77,
          "length" : 13
        },
        {
          "activity" : "generate1",
          "start" : 86,
          "length" : 15
        },
        {
          "activity" : "generate2",
          "start" : 95,
          "length" : 11
        }
      ]
    },
    {
      "name" : "fsh-generated/resources/PlanDefinition-GetDiagnoses.json",
      "size" : 2420,
      "processes" : [
        {
          "activity" : "loadResources",
          "start" : 52,
          "length" : 3
        },
        {
          "activity" : "load",
          "start" : 53,
          "length" : 5
        },
        {
          "activity" : "generateNarratives",
          "start" : 56,
          "length" : 19
        },
        {
          "activity" : "validate",
          "start" : 77,
          "length" : 7
        },
        {
          "activity" : "generate1",
          "start" : 86,
          "length" : 14
        },
        {
          "activity" : "generate2",
          "start" : 95,
          "length" : 9
        }
      ]
    },
    {
      "name" : "fsh-generated/resources/PlanDefinition-GetRecommendations.json",
      "size" : 2671,
      "processes" : [
        {
          "activity" : "loadResources",
          "start" : 52,
          "length" : 2
        },
        {
          "activity" : "load",
          "start" : 53,
          "length" : 4
        },
        {
          "activity" : "generateNarratives",
          "start" : 56,
          "length" : 26
        },
        {
          "activity" : "validate",
          "start" : 77,
          "length" : 12
        },
        {
          "activity" : "generate1",
          "start" : 86,
          "length" : 14
        },
        {
          "activity" : "generate2",
          "start" : 95,
          "length" : 9
        },
        {
          "activity" : "generateValidationPack",
          "start" : 118,
          "length" : 1
        }
      ]
    },
    {
      "name" : "fsh-generated/resources/Questionnaire-q-collect-information-a.json",
      "size" : 11247,
      "processes" : [
        {
          "activity" : "loadResources",
          "start" : 52,
          "length" : 3
        },
        {
          "activity" : "load",
          "start" : 53,
          "length" : 15
        },
        {
          "activity" : "checkR4R4B",
          "start" : 55,
          "length" : 1
        },
        {
          "activity" : "generateNarratives",
          "start" : 56,
          "length" : 14
        },
        {
          "activity" : "validate",
          "start" : 77,
          "length" : 1440
        },
        {
          "activity" : "generate1",
          "start" : 86,
          "length" : 37
        },
        {
          "activity" : "generate2",
          "start" : 95,
          "length" : 32
        },
        {
          "activity" : "generateValidationPack",
          "start" : 118,
          "length" : 2
        }
      ]
    },
    {
      "name" : "fsh-generated/resources/QuestionnaireResponse-qresponse-v.json",
      "size" : 1261,
      "processes" : [
        {
          "activity" : "loadResources",
          "start" : 52,
          "length" : 3
        },
        {
          "activity" : "generateNarratives",
          "start" : 56,
          "length" : 2
        },
        {
          "activity" : "validate",
          "start" : 85,
          "length" : 3
        },
        {
          "activity" : "generate1",
          "start" : 86,
          "length" : 22
        },
        {
          "activity" : "responsesForQuestionnaire",
          "start" : 95,
          "length" : 1
        },
        {
          "activity" : "generate2",
          "start" : 95,
          "length" : 19
        }
      ]
    },
    {
      "name" : "fsh-generated/resources/RequestGroup-Inline-Instance-for-radiology-getdiagnoses-response.json",
      "size" : 1051,
      "processes" : [
        {
          "activity" : "loadResources",
          "start" : 52,
          "length" : 2
        },
        {
          "activity" : "load-configure",
          "start" : 55,
          "length" : 1
        },
        {
          "activity" : "generateNarratives",
          "start" : 56,
          "length" : 2
        },
        {
          "activity" : "validate",
          "start" : 85,
          "length" : 5
        },
        {
          "activity" : "generate1",
          "start" : 86,
          "length" : 11
        },
        {
          "activity" : "generate2",
          "start" : 95,
          "length" : 24
        }
      ]
    },
    {
      "name" : "fsh-generated/resources/RequestGroup-getdatatocollect-a-response-group.json",
      "size" : 445,
      "processes" : [
        {
          "activity" : "loadResources",
          "start" : 52,
          "length" : 2
        },
        {
          "activity" : "generateNarratives",
          "start" : 56,
          "length" : 2
        },
        {
          "activity" : "validate",
          "start" : 85,
          "length" : 1
        },
        {
          "activity" : "generate1",
          "start" : 86,
          "length" : 10
        },
        {
          "activity" : "generate2",
          "start" : 95,
          "length" : 21
        }
      ]
    },
    {
      "name" : "fsh-generated/resources/RequestGroup-getrecommendations-a-response-group.json",
      "size" : 12428,
      "processes" : [
        {
          "activity" : "loadResources",
          "start" : 52,
          "length" : 4
        },
        {
          "activity" : "generateNarratives",
          "start" : 56,
          "length" : 11
        },
        {
          "activity" : "validate",
          "start" : 85,
          "length" : 428
        },
        {
          "activity" : "generate1",
          "start" : 86,
          "length" : 19
        },
        {
          "activity" : "generate2",
          "start" : 95,
          "length" : 35
        }
      ]
    },
    {
      "name" : "fsh-generated/resources/RequestGroup-getrecommendations-r-response-1.json",
      "size" : 5259,
      "processes" : [
        {
          "activity" : "loadResources",
          "start" : 52,
          "length" : 3
        },
        {
          "activity" : "generateNarratives",
          "start" : 56,
          "length" : 5
        },
        {
          "activity" : "validate",
          "start" : 85,
          "length" : 94
        },
        {
          "activity" : "generate1",
          "start" : 86,
          "length" : 14
        },
        {
          "activity" : "generate2",
          "start" : 95,
          "length" : 26
        }
      ]
    },
    {
      "name" : "fsh-generated/resources/ServiceRequest-ct-head-wo-iv-contrast.json",
      "size" : 536,
      "processes" : [
        {
          "activity" : "loadResources",
          "start" : 52,
          "length" : 3
        },
        {
          "activity" : "checkR4R4B",
          "start" : 55,
          "length" : 1
        },
        {
          "activity" : "generateNarratives",
          "start" : 56,
          "length" : 2
        },
        {
          "activity" : "validate",
          "start" : 85,
          "length" : 1
        },
        {
          "activity" : "generate1",
          "start" : 86,
          "length" : 8
        },
        {
          "activity" : "generate2",
          "start" : 96,
          "length" : 15
        }
      ]
    },
    {
      "name" : "fsh-generated/resources/ServiceRequest-proposed-ct-head-wo-iv-contrast.json",
      "size" : 670,
      "processes" : [
        {
          "activity" : "loadResources",
          "start" : 52,
          "length" : 2
        },
        {
          "activity" : "generateNarratives",
          "start" : 56,
          "length" : 1
        },
        {
          "activity" : "validate",
          "start" : 85,
          "length" : 2
        },
        {
          "activity" : "generate1",
          "start" : 86,
          "length" : 9
        },
        {
          "activity" : "generate2",
          "start" : 96,
          "length" : 13
        }
      ]
    },
    {
      "name" : "fsh-generated/resources/ServiceRequest-proposed-ct-head-wo-w-iv-contrast.json",
      "size" : 674,
      "processes" : [
        {
          "activity" : "loadResources",
          "start" : 52,
          "length" : 2
        },
        {
          "activity" : "generateNarratives",
          "start" : 56,
          "length" : 1
        },
        {
          "activity" : "validate",
          "start" : 85,
          "length" : 1
        },
        {
          "activity" : "generate1",
          "start" : 86,
          "length" : 10
        },
        {
          "activity" : "generate2",
          "start" : 96,
          "length" : 10
        }
      ]
    },
    {
      "name" : "fsh-generated/resources/ServiceRequest-proposed-mr-head-wo-iv-contrast.json",
      "size" : 670,
      "processes" : [
        {
          "activity" : "loadResources",
          "start" : 52,
          "length" : 3
        },
        {
          "activity" : "generateNarratives",
          "start" : 56,
          "length" : 1
        },
        {
          "activity" : "validate",
          "start" : 85,
          "length" : 1
        },
        {
          "activity" : "generate1",
          "start" : 86,
          "length" : 9
        },
        {
          "activity" : "generate2",
          "start" : 96,
          "length" : 14
        }
      ]
    },
    {
      "name" : "fsh-generated/resources/ServiceRequest-pss-ct-head-wo-iv-contrast.json",
      "size" : 665,
      "processes" : [
        {
          "activity" : "loadResources",
          "start" : 52,
          "length" : 2
        },
        {
          "activity" : "load-configure",
          "start" : 55,
          "length" : 1
        },
        {
          "activity" : "generateNarratives",
          "start" : 56,
          "length" : 1
        },
        {
          "activity" : "validate",
          "start" : 85,
          "length" : 1
        },
        {
          "activity" : "generate1",
          "start" : 86,
          "length" : 9
        },
        {
          "activity" : "generate2",
          "start" : 96,
          "length" : 15
        }
      ]
    },
    {
      "name" : "fsh-generated/resources/StructureDefinition-AnswerOptionAdditionalCode.json",
      "size" : 1405,
      "processes" : [
        {
          "activity" : "loadResources",
          "start" : 52,
          "length" : 3
        },
        {
          "activity" : "load",
          "start" : 53,
          "length" : 8
        },
        {
          "activity" : "generateSnapshots",
          "start" : 53,
          "length" : 13
        },
        {
          "activity" : "generateNarratives",
          "start" : 56,
          "length" : 21
        },
        {
          "activity" : "validate",
          "start" : 69,
          "length" : 152
        },
        {
          "activity" : "generate1",
          "start" : 86,
          "length" : 33
        },
        {
          "activity" : "generate2",
          "start" : 96,
          "length" : 160
        },
        {
          "activity" : "generate2",
          "start" : 103,
          "length" : 512
        },
        {
          "activity" : "generateValidationPack",
          "start" : 118,
          "length" : 2
        }
      ]
    },
    {
      "name" : "fsh-generated/resources/StructureDefinition-CodeValueSet.json",
      "size" : 1684,
      "processes" : [
        {
          "activity" : "loadResources",
          "start" : 52,
          "length" : 2
        },
        {
          "activity" : "load",
          "start" : 53,
          "length" : 6
        },
        {
          "activity" : "generateSnapshots",
          "start" : 53,
          "length" : 28
        },
        {
          "activity" : "generateNarratives",
          "start" : 56,
          "length" : 7
        },
        {
          "activity" : "validate",
          "start" : 69,
          "length" : 79
        },
        {
          "activity" : "generate1",
          "start" : 86,
          "length" : 33
        },
        {
          "activity" : "generate2",
          "start" : 96,
          "length" : 190
        },
        {
          "activity" : "generate2",
          "start" : 104,
          "length" : 110
        },
        {
          "activity" : "generateValidationPack",
          "start" : 118,
          "length" : 1
        }
      ]
    },
    {
      "name" : "fsh-generated/resources/StructureDefinition-PSSDataAcquisitionForm.json",
      "size" : 1403,
      "processes" : [
        {
          "activity" : "loadResources",
          "start" : 52,
          "length" : 3
        },
        {
          "activity" : "load",
          "start" : 53,
          "length" : 5
        },
        {
          "activity" : "generateSnapshots",
          "start" : 53,
          "length" : 119
        },
        {
          "activity" : "generateNarratives",
          "start" : 56,
          "length" : 52
        },
        {
          "activity" : "validate",
          "start" : 69,
          "length" : 396
        },
        {
          "activity" : "checkConformanceResources",
          "start" : 79,
          "length" : 1
        },
        {
          "activity" : "generate1",
          "start" : 86,
          "length" : 165
        },
        {
          "activity" : "generate2",
          "start" : 96,
          "length" : 630
        },
        {
          "activity" : "generate2",
          "start" : 104,
          "length" : 571
        },
        {
          "activity" : "generateValidationPack",
          "start" : 118,
          "length" : 7
        },
        {
          "activity" : "scanExamplesForR5",
          "start" : 129,
          "length" : 2
        }
      ]
    },
    {
      "name" : "fsh-generated/resources/StructureDefinition-PSSPatient.json",
      "size" : 2207,
      "processes" : [
        {
          "activity" : "loadResources",
          "start" : 52,
          "length" : 2
        },
        {
          "activity" : "load",
          "start" : 53,
          "length" : 6
        },
        {
          "activity" : "generateSnapshots",
          "start" : 53,
          "length" : 100
        },
        {
          "activity" : "generateNarratives",
          "start" : 56,
          "length" : 34
        },
        {
          "activity" : "validate",
          "start" : 69,
          "length" : 348
        },
        {
          "activity" : "scanForUsageStats",
          "start" : 79,
          "length" : 1
        },
        {
          "activity" : "generate1",
          "start" : 86,
          "length" : 160
        },
        {
          "activity" : "generate2",
          "start" : 97,
          "length" : 484
        },
        {
          "activity" : "generate2",
          "start" : 104,
          "length" : 425
        },
        {
          "activity" : "generateValidationPack",
          "start" : 118,
          "length" : 7
        },
        {
          "activity" : "scanExamplesForR5",
          "start" : 129,
          "length" : 1
        }
      ]
    },
    {
      "name" : "fsh-generated/resources/StructureDefinition-PSSRelevantAge.json",
      "size" : 1358,
      "processes" : [
        {
          "activity" : "loadResources",
          "start" : 52,
          "length" : 3
        },
        {
          "activity" : "load",
          "start" : 53,
          "length" : 5
        },
        {
          "activity" : "generateSnapshots",
          "start" : 53,
          "length" : 39
        },
        {
          "activity" : "generateNarratives",
          "start" : 57,
          "length" : 11
        },
        {
          "activity" : "validate",
          "start" : 70,
          "length" : 40
        },
        {
          "activity" : "generate1",
          "start" : 87,
          "length" : 32
        },
        {
          "activity" : "generate2",
          "start" : 97,
          "length" : 83
        },
        {
          "activity" : "generate2",
          "start" : 105,
          "length" : 47
        },
        {
          "activity" : "generateValidationPack",
          "start" : 118,
          "length" : 1
        }
      ]
    },
    {
      "name" : "fsh-generated/resources/StructureDefinition-PSSRequest.json",
      "size" : 3323,
      "processes" : [
        {
          "activity" : "loadResources",
          "start" : 52,
          "length" : 3
        },
        {
          "activity" : "load",
          "start" : 53,
          "length" : 6
        },
        {
          "activity" : "generateSnapshots",
          "start" : 53,
          "length" : 39
        },
        {
          "activity" : "generateNarratives",
          "start" : 57,
          "length" : 12
        },
        {
          "activity" : "validate",
          "start" : 70,
          "length" : 54
        },
        {
          "activity" : "generate1",
          "start" : 87,
          "length" : 46
        },
        {
          "activity" : "generate2",
          "start" : 97,
          "length" : 100
        },
        {
          "activity" : "generate2",
          "start" : 105,
          "length" : 61
        },
        {
          "activity" : "generateValidationPack",
          "start" : 118,
          "length" : 2
        }
      ]
    },
    {
      "name" : "fsh-generated/resources/StructureDefinition-PSSRequestBundle.json",
      "size" : 648,
      "processes" : [
        {
          "activity" : "loadResources",
          "start" : 52,
          "length" : 3
        },
        {
          "activity" : "load",
          "start" : 53,
          "length" : 5
        },
        {
          "activity" : "generateSnapshots",
          "start" : 53,
          "length" : 66
        },
        {
          "activity" : "generateNarratives",
          "start" : 57,
          "length" : 18
        },
        {
          "activity" : "validate",
          "start" : 70,
          "length" : 219
        },
        {
          "activity" : "generate1",
          "start" : 87,
          "length" : 103
        },
        {
          "activity" : "generate2",
          "start" : 97,
          "length" : 172
        },
        {
          "activity" : "generate2",
          "start" : 105,
          "length" : 184
        },
        {
          "activity" : "generateValidationPack",
          "start" : 118,
          "length" : 5
        }
      ]
    },
    {
      "name" : "fsh-generated/resources/StructureDefinition-PSSResponse.json",
      "size" : 4579,
      "processes" : [
        {
          "activity" : "loadResources",
          "start" : 52,
          "length" : 4
        },
        {
          "activity" : "load",
          "start" : 53,
          "length" : 7
        },
        {
          "activity" : "generateSnapshots",
          "start" : 54,
          "length" : 44
        },
        {
          "activity" : "load-configure",
          "start" : 55,
          "length" : 1
        },
        {
          "activity" : "generateNarratives",
          "start" : 57,
          "length" : 14
        },
        {
          "activity" : "validate",
          "start" : 70,
          "length" : 62
        },
        {
          "activity" : "scanForUsageStats",
          "start" : 79,
          "length" : 1
        },
        {
          "activity" : "generate1",
          "start" : 87,
          "length" : 56
        },
        {
          "activity" : "generate2",
          "start" : 97,
          "length" : 92
        },
        {
          "activity" : "generate2",
          "start" : 105,
          "length" : 61
        },
        {
          "activity" : "generateValidationPack",
          "start" : 118,
          "length" : 2
        },
        {
          "activity" : "scanProfilesForR5",
          "start" : 129,
          "length" : 1
        },
        {
          "activity" : "scanExamplesForR5",
          "start" : 129,
          "length" : 1
        }
      ]
    },
    {
      "name" : "fsh-generated/resources/StructureDefinition-PSSResponseBundle.json",
      "size" : 791,
      "processes" : [
        {
          "activity" : "loadResources",
          "start" : 52,
          "length" : 3
        },
        {
          "activity" : "load",
          "start" : 53,
          "length" : 4
        },
        {
          "activity" : "generateSnapshots",
          "start" : 54,
          "length" : 49
        },
        {
          "activity" : "generateNarratives",
          "start" : 57,
          "length" : 16
        },
        {
          "activity" : "validate",
          "start" : 70,
          "length" : 206
        },
        {
          "activity" : "generate1",
          "start" : 87,
          "length" : 104
        },
        {
          "activity" : "generate2",
          "start" : 97,
          "length" : 180
        },
        {
          "activity" : "generate2",
          "start" : 105,
          "length" : 161
        },
        {
          "activity" : "generateValidationPack",
          "start" : 118,
          "length" : 4
        }
      ]
    },
    {
      "name" : "fsh-generated/resources/StructureDefinition-PSSResponseCommunicationRequest.json",
      "size" : 785,
      "processes" : [
        {
          "activity" : "loadResources",
          "start" : 52,
          "length" : 2
        },
        {
          "activity" : "load",
          "start" : 53,
          "length" : 5
        },
        {
          "activity" : "generateSnapshots",
          "start" : 54,
          "length" : 43
        },
        {
          "activity" : "generateNarratives",
          "start" : 57,
          "length" : 15
        },
        {
          "activity" : "validate",
          "start" : 70,
          "length" : 211
        },
        {
          "activity" : "generate1",
          "start" : 87,
          "length" : 84
        },
        {
          "activity" : "generate2",
          "start" : 98,
          "length" : 190
        },
        {
          "activity" : "generate2",
          "start" : 105,
          "length" : 134
        },
        {
          "activity" : "generateValidationPack",
          "start" : 118,
          "length" : 3
        }
      ]
    },
    {
      "name" : "fsh-generated/resources/StructureDefinition-PSSResponseMedicationRequest.json",
      "size" : 820,
      "processes" : [
        {
          "activity" : "loadResources",
          "start" : 52,
          "length" : 3
        },
        {
          "activity" : "load",
          "start" : 53,
          "length" : 4
        },
        {
          "activity" : "generateSnapshots",
          "start" : 54,
          "length" : 44
        },
        {
          "activity" : "generateNarratives",
          "start" : 57,
          "length" : 23
        },
        {
          "activity" : "validate",
          "start" : 70,
          "length" : 294
        },
        {
          "activity" : "scanForUsageStats",
          "start" : 79,
          "length" : 1
        },
        {
          "activity" : "generate1",
          "start" : 87,
          "length" : 135
        },
        {
          "activity" : "generate2",
          "start" : 98,
          "length" : 245
        },
        {
          "activity" : "generate2",
          "start" : 105,
          "length" : 221
        },
        {
          "activity" : "generateValidationPack",
          "start" : 118,
          "length" : 6
        },
        {
          "activity" : "scanExamplesForR5",
          "start" : 129,
          "length" : 1
        }
      ]
    },
    {
      "name" : "fsh-generated/resources/StructureDefinition-PSSResponseRequestGroup.json",
      "size" : 1855,
      "processes" : [
        {
          "activity" : "loadResources",
          "start" : 52,
          "length" : 28
        },
        {
          "activity" : "load",
          "start" : 53,
          "length" : 5
        },
        {
          "activity" : "generateSnapshots",
          "start" : 54,
          "length" : 50
        },
        {
          "activity" : "generateNarratives",
          "start" : 57,
          "length" : 29
        },
        {
          "activity" : "validate",
          "start" : 71,
          "length" : 234
        },
        {
          "activity" : "generate1",
          "start" : 87,
          "length" : 175
        },
        {
          "activity" : "generate2",
          "start" : 98,
          "length" : 248
        },
        {
          "activity" : "generate2",
          "start" : 105,
          "length" : 230
        },
        {
          "activity" : "generateValidationPack",
          "start" : 118,
          "length" : 7
        },
        {
          "activity" : "scanExamplesForR5",
          "start" : 129,
          "length" : 1
        }
      ]
    },
    {
      "name" : "fsh-generated/resources/StructureDefinition-PSSResponseServiceRequest.json",
      "size" : 1072,
      "processes" : [
        {
          "activity" : "loadResources",
          "start" : 52,
          "length" : 5
        },
        {
          "activity" : "load",
          "start" : 53,
          "length" : 5
        },
        {
          "activity" : "generateSnapshots",
          "start" : 54,
          "length" : 32
        },
        {
          "activity" : "generateNarratives",
          "start" : 57,
          "length" : 23
        },
        {
          "activity" : "validate",
          "start" : 71,
          "length" : 118
        },
        {
          "activity" : "scanForUsageStats",
          "start" : 79,
          "length" : 1
        },
        {
          "activity" : "generate1",
          "start" : 87,
          "length" : 101
        },
        {
          "activity" : "generate2",
          "start" : 98,
          "length" : 149
        },
        {
          "activity" : "generate2",
          "start" : 106,
          "length" : 123
        },
        {
          "activity" : "generateValidationPack",
          "start" : 118,
          "length" : 5
        }
      ]
    },
    {
      "name" : "fsh-generated/resources/StructureDefinition-PSSStructuredRating.json",
      "size" : 4380,
      "processes" : [
        {
          "activity" : "loadResources",
          "start" : 52,
          "length" : 4
        },
        {
          "activity" : "load",
          "start" : 53,
          "length" : 7
        },
        {
          "activity" : "generateSnapshots",
          "start" : 54,
          "length" : 12
        },
        {
          "activity" : "generateNarratives",
          "start" : 57,
          "length" : 28
        },
        {
          "activity" : "validate",
          "start" : 71,
          "length" : 102
        },
        {
          "activity" : "checkConformanceResources",
          "start" : 79,
          "length" : 1
        },
        {
          "activity" : "generate1",
          "start" : 87,
          "length" : 94
        },
        {
          "activity" : "generate2",
          "start" : 99,
          "length" : 100
        },
        {
          "activity" : "generate2",
          "start" : 106,
          "length" : 57
        },
        {
          "activity" : "generateValidationPack",
          "start" : 118,
          "length" : 3
        },
        {
          "activity" : "scanExamplesForR5",
          "start" : 129,
          "length" : 1
        }
      ]
    },
    {
      "name" : "fsh-generated/resources/Task-collect-information-a.json",
      "size" : 802,
      "processes" : [
        {
          "activity" : "loadResources",
          "start" : 52,
          "length" : 4
        },
        {
          "activity" : "generateNarratives",
          "start" : 57,
          "length" : 3
        },
        {
          "activity" : "validate",
          "start" : 85,
          "length" : 2
        },
        {
          "activity" : "generate1",
          "start" : 88,
          "length" : 10
        },
        {
          "activity" : "generate2",
          "start" : 99,
          "length" : 14
        }
      ]
    },
    {
      "name" : "fsh-generated/resources/Task-propose-3074219.json",
      "size" : 744,
      "processes" : [
        {
          "activity" : "loadResources",
          "start" : 52,
          "length" : 4
        },
        {
          "activity" : "generateNarratives",
          "start" : 57,
          "length" : 1
        },
        {
          "activity" : "validate",
          "start" : 85,
          "length" : 2
        },
        {
          "activity" : "generate1",
          "start" : 88,
          "length" : 9
        },
        {
          "activity" : "generate2",
          "start" : 99,
          "length" : 12
        }
      ]
    },
    {
      "name" : "fsh-generated/resources/Task-propose-3074220.json",
      "size" : 744,
      "processes" : [
        {
          "activity" : "loadResources",
          "start" : 52,
          "length" : 4
        },
        {
          "activity" : "generateNarratives",
          "start" : 57,
          "length" : 1
        },
        {
          "activity" : "validate",
          "start" : 85,
          "length" : 2
        },
        {
          "activity" : "generate1",
          "start" : 88,
          "length" : 10
        },
        {
          "activity" : "generate2",
          "start" : 99,
          "length" : 11
        }
      ]
    },
    {
      "name" : "fsh-generated/resources/Task-propose-3074221.json",
      "size" : 744,
      "processes" : [
        {
          "activity" : "loadResources",
          "start" : 52,
          "length" : 4
        },
        {
          "activity" : "generateNarratives",
          "start" : 57,
          "length" : 1
        },
        {
          "activity" : "validate",
          "start" : 85,
          "length" : 3
        },
        {
          "activity" : "generate1",
          "start" : 88,
          "length" : 9
        },
        {
          "activity" : "generate2",
          "start" : 99,
          "length" : 8
        }
      ]
    },
    {
      "name" : "fsh-generated/resources/Task-propose-3074222.json",
      "size" : 744,
      "processes" : [
        {
          "activity" : "loadResources",
          "start" : 52,
          "length" : 4
        },
        {
          "activity" : "load-configure",
          "start" : 55,
          "length" : 1
        },
        {
          "activity" : "generateNarratives",
          "start" : 57,
          "length" : 1
        },
        {
          "activity" : "validate",
          "start" : 85,
          "length" : 2
        },
        {
          "activity" : "generate1",
          "start" : 88,
          "length" : 10
        },
        {
          "activity" : "generate2",
          "start" : 99,
          "length" : 8
        }
      ]
    },
    {
      "name" : "fsh-generated/resources/Task-propose-5000246.json",
      "size" : 744,
      "processes" : [
        {
          "activity" : "loadResources",
          "start" : 52,
          "length" : 3
        },
        {
          "activity" : "generateNarratives",
          "start" : 57,
          "length" : 2
        },
        {
          "activity" : "validate",
          "start" : 85,
          "length" : 2
        },
        {
          "activity" : "generate1",
          "start" : 88,
          "length" : 9
        },
        {
          "activity" : "generate2",
          "start" : 99,
          "length" : 8
        }
      ]
    },
    {
      "name" : "fsh-generated/resources/ValueSet-BacterialCodes.json",
      "size" : 1761,
      "processes" : [
        {
          "activity" : "loadResources",
          "start" : 52,
          "length" : 4
        },
        {
          "activity" : "load",
          "start" : 52,
          "length" : 5
        },
        {
          "activity" : "generateNarratives",
          "start" : 57,
          "length" : 308
        },
        {
          "activity" : "validate",
          "start" : 63,
          "length" : 209
        },
        {
          "activity" : "generate1",
          "start" : 88,
          "length" : 13
        },
        {
          "activity" : "generate2",
          "start" : 99,
          "length" : 331
        },
        {
          "activity" : "generateValidationPack",
          "start" : 118,
          "length" : 1
        }
      ]
    },
    {
      "name" : "fsh-generated/resources/ValueSet-CandidaCodes.json",
      "size" : 1918,
      "processes" : [
        {
          "activity" : "loadResources",
          "start" : 52,
          "length" : 4
        },
        {
          "activity" : "load",
          "start" : 52,
          "length" : 5
        },
        {
          "activity" : "generateNarratives",
          "start" : 57,
          "length" : 199
        },
        {
          "activity" : "validate",
          "start" : 63,
          "length" : 414
        },
        {
          "activity" : "generate1",
          "start" : 88,
          "length" : 14
        },
        {
          "activity" : "generate2",
          "start" : 99,
          "length" : 245
        }
      ]
    },
    {
      "name" : "fsh-generated/resources/ValueSet-ChlamydiaCodes.json",
      "size" : 2023,
      "processes" : [
        {
          "activity" : "loadResources",
          "start" : 52,
          "length" : 4
        },
        {
          "activity" : "load",
          "start" : 52,
          "length" : 5
        },
        {
          "activity" : "generateNarratives",
          "start" : 57,
          "length" : 400
        },
        {
          "activity" : "validate",
          "start" : 63,
          "length" : 773
        },
        {
          "activity" : "generate1",
          "start" : 88,
          "length" : 14
        },
        {
          "activity" : "generate2",
          "start" : 99,
          "length" : 437
        }
      ]
    },
    {
      "name" : "fsh-generated/resources/ValueSet-CompromisedImmuneSystemCodes.json",
      "size" : 2345,
      "processes" : [
        {
          "activity" : "loadResources",
          "start" : 52,
          "length" : 4
        },
        {
          "activity" : "load",
          "start" : 52,
          "length" : 5
        },
        {
          "activity" : "generateNarratives",
          "start" : 58,
          "length" : 962
        },
        {
          "activity" : "validate",
          "start" : 64,
          "length" : 1283
        },
        {
          "activity" : "generate1",
          "start" : 88,
          "length" : 15
        },
        {
          "activity" : "generate2",
          "start" : 100,
          "length" : 723
        }
      ]
    },
    {
      "name" : "fsh-generated/resources/ValueSet-GonokokCodes.json",
      "size" : 1956,
      "processes" : [
        {
          "activity" : "loadResources",
          "start" : 52,
          "length" : 3
        },
        {
          "activity" : "load",
          "start" : 52,
          "length" : 4
        },
        {
          "activity" : "checkR4R4B",
          "start" : 55,
          "length" : 1
        },
        {
          "activity" : "generateNarratives",
          "start" : 59,
          "length" : 391
        },
        {
          "activity" : "validate",
          "start" : 65,
          "length" : 591
        },
        {
          "activity" : "generate1",
          "start" : 88,
          "length" : 13
        },
        {
          "activity" : "generate2",
          "start" : 100,
          "length" : 424
        },
        {
          "activity" : "generateValidationPack",
          "start" : 118,
          "length" : 1
        }
      ]
    },
    {
      "name" : "fsh-generated/resources/ValueSet-MycoplasmaCodes.json",
      "size" : 1766,
      "processes" : [
        {
          "activity" : "loadResources",
          "start" : 52,
          "length" : 4
        },
        {
          "activity" : "load",
          "start" : 52,
          "length" : 5
        },
        {
          "activity" : "generateNarratives",
          "start" : 59,
          "length" : 199
        },
        {
          "activity" : "validate",
          "start" : 66,
          "length" : 199
        },
        {
          "activity" : "generate1",
          "start" : 88,
          "length" : 15
        },
        {
          "activity" : "generate2",
          "start" : 101,
          "length" : 230
        }
      ]
    },
    {
      "name" : "fsh-generated/resources/ValueSet-OncologyPatientCodes.json",
      "size" : 2306,
      "processes" : [
        {
          "activity" : "loadResources",
          "start" : 52,
          "length" : 4
        },
        {
          "activity" : "load",
          "start" : 52,
          "length" : 5
        },
        {
          "activity" : "generateNarratives",
          "start" : 59,
          "length" : 970
        },
        {
          "activity" : "validate",
          "start" : 66,
          "length" : 804
        },
        {
          "activity" : "generate1",
          "start" : 88,
          "length" : 15
        },
        {
          "activity" : "generate2",
          "start" : 101,
          "length" : 701
        }
      ]
    },
    {
      "name" : "fsh-generated/resources/ValueSet-OtherCodes.json",
      "size" : 1911,
      "processes" : [
        {
          "activity" : "loadResources",
          "start" : 52,
          "length" : 4
        },
        {
          "activity" : "load",
          "start" : 52,
          "length" : 4
        },
        {
          "activity" : "generateNarratives",
          "start" : 60,
          "length" : 199
        },
        {
          "activity" : "validate",
          "start" : 67,
          "length" : 417
        },
        {
          "activity" : "generate1",
          "start" : 88,
          "length" : 14
        },
        {
          "activity" : "generate2",
          "start" : 102,
          "length" : 238
        },
        {
          "activity" : "generateValidationPack",
          "start" : 118,
          "length" : 1
        }
      ]
    },
    {
      "name" : "fsh-generated/resources/ValueSet-PSSRatingTypesVS.json",
      "size" : 481,
      "processes" : [
        {
          "activity" : "loadResources",
          "start" : 52,
          "length" : 4
        },
        {
          "activity" : "load",
          "start" : 53,
          "length" : 4
        },
        {
          "activity" : "generateNarratives",
          "start" : 60,
          "length" : 3
        },
        {
          "activity" : "validate",
          "start" : 67,
          "length" : 5
        },
        {
          "activity" : "generate1",
          "start" : 88,
          "length" : 11
        },
        {
          "activity" : "generate2",
          "start" : 102,
          "length" : 49
        }
      ]
    },
    {
      "name" : "fsh-generated/resources/ValueSet-PregnancyCodes.json",
      "size" : 2070,
      "processes" : [
        {
          "activity" : "loadResources",
          "start" : 52,
          "length" : 4
        },
        {
          "activity" : "load",
          "start" : 53,
          "length" : 4
        },
        {
          "activity" : "generateNarratives",
          "start" : 60,
          "length" : 1095
        },
        {
          "activity" : "validate",
          "start" : 67,
          "length" : 819
        },
        {
          "activity" : "generate1",
          "start" : 88,
          "length" : 14
        },
        {
          "activity" : "generate2",
          "start" : 102,
          "length" : 610
        }
      ]
    },
    {
      "name" : "fsh-generated/resources/ValueSet-TrichomonasCodes.json",
      "size" : 1827,
      "processes" : [
        {
          "activity" : "loadResources",
          "start" : 52,
          "length" : 4
        },
        {
          "activity" : "load",
          "start" : 53,
          "length" : 5
        },
        {
          "activity" : "generateNarratives",
          "start" : 61,
          "length" : 201
        },
        {
          "activity" : "validate",
          "start" : 68,
          "length" : 389
        },
        {
          "activity" : "generate1",
          "start" : 88,
          "length" : 13
        },
        {
          "activity" : "generate2",
          "start" : 103,
          "length" : 244
        },
        {
          "activity" : "generateValidationPack",
          "start" : 118,
          "length" : 1
        }
      ]
    }
  ]
}
