{
  "codeSystems" : [
    {
      "url" : "https://www.ehealth.fgov.be/standards/fhir/medication/CodeSystem/radiology-exposure-rating",
      "version" : "1.0.0",
      "status" : "draft",
      "name" : "RadiologyExposureRatingCS",
      "title" : "Radiation exposure rating",
      "description" : "Radiation exposure rating.",
      "uses" : {
      },
      "ValueSet-radiation-exposure-rating-vs.html" : "Radiation exposure rating"
    },
    {
      "url" : "https://www.ehealth.fgov.be/standards/fhir/medication/CodeSystem/recommendation-rating",
      "version" : "1.0.0",
      "status" : "draft",
      "name" : "RecommendationRatingCS",
      "title" : "Recommendation rating",
      "description" : "Recommendation rating.",
      "uses" : {
      },
      "ValueSet-recommendation-rating-vs.html" : "Recommendation rating"
    }
  ]
}
